<?xml version="1.0" encoding="UTF-8" standalone="no"?>
<!DOCTYPE tiles-definitions PUBLIC "-//Apache Software Foundation//DTD Tiles Configuration 2.1//EN" "http://tiles.apache.org/dtds/tiles-config_2_1.dtd">
<tiles-definitions>
    <definition extends="default" name="sizeproportions/list">
        <put-attribute name="body" value="/WEB-INF/views/sizeproportions/list.jspx"/>
    </definition>
<definition extends="default" name="sizeproportions/show">
        <put-attribute name="body" value="/WEB-INF/views/sizeproportions/show.jspx"/>
    </definition>
<definition extends="default" name="sizeproportions/create">
        <put-attribute name="body" value="/WEB-INF/views/sizeproportions/create.jspx"/>
    </definition>
<definition extends="default" name="sizeproportions/update">
        <put-attribute name="body" value="/WEB-INF/views/sizeproportions/update.jspx"/>
    </definition>
</tiles-definitions>
